deadpan_api/__init__.py
deadpan_api/genericFileAPI/__init__.py
deadpan_api/imageAPI/__init__.py
deadpan_api/jsonAPI/__init__.py
deadpan_api/spreadsheetAPI/__init__.py
deadpan_api/textAPI/__init__.py
deadpan_api-0.1.0.data/data/VERSION
deadpan_api-0.1.0.dist-info/METADATA
deadpan_api-0.1.0.dist-info/WHEEL
deadpan_api-0.1.0.dist-info/top_level.txt
deadpan_api-0.1.0.dist-info/RECORD
